MANIFEST.in
README.md
setup.cfg
setup.py
defichainUtils/__init__.py
defichainUtils/defichainUtils.py
defichainUtils.egg-info/PKG-INFO
defichainUtils.egg-info/SOURCES.txt
defichainUtils.egg-info/dependency_links.txt
defichainUtils.egg-info/top_level.txt
defichainUtils/__pycache__/defichainUtils.cpython-39.pyc
defichainUtils/utils/CustomTx.py
defichainUtils/utils/CustomTxDecode.py
defichainUtils/utils/GovVariablesAttributes.py
defichainUtils/utils/ParamType.py
defichainUtils/utils/__init__.py
defichainUtils/utils/base58.py
defichainUtils/utils/bech32.py
defichainUtils/utils/chain.py
defichainUtils/utils/utils.py
defichainUtils/utils/__pycache__/CustomTx.cpython-39.pyc
defichainUtils/utils/__pycache__/CustomTxDecode.cpython-39.pyc
defichainUtils/utils/__pycache__/ParamType.cpython-39.pyc
defichainUtils/utils/__pycache__/__init__.cpython-39.pyc
defichainUtils/utils/__pycache__/base58.cpython-39.pyc
defichainUtils/utils/__pycache__/bech32.cpython-39.pyc
defichainUtils/utils/__pycache__/chain.cpython-39.pyc
defichainUtils/utils/__pycache__/utils.cpython-39.pyc