Metadata-Version: 2.1
Name: defichainUtils
Version: 0.0.32
Summary: DefichainUtils
Home-page: UNKNOWN
Author: RupineLabs
Author-email: <abc@def.com>
License: UNKNOWN
Keywords: web3
Platform: UNKNOWN
Classifier: Development Status :: 1 - Planning
Classifier: Intended Audience :: Developers
Classifier: Programming Language :: Python :: 3
Classifier: Operating System :: Unix
Classifier: Operating System :: MacOS :: MacOS X
Classifier: Operating System :: Microsoft :: Windows
